MANIFEST.in
README.rst
setup.py
src/nose_performance.egg-info/PKG-INFO
src/nose_performance.egg-info/SOURCES.txt
src/nose_performance.egg-info/dependency_links.txt
src/nose_performance.egg-info/entry_points.txt
src/nose_performance.egg-info/not-zip-safe
src/nose_performance.egg-info/requires.txt
src/nose_performance.egg-info/top_level.txt
src/noseperf/__init__.py
src/noseperf/plugin.py
src/noseperf/stacks.py
src/noseperf/testcases.py
src/noseperf/util.py
src/noseperf/wrappers/__init__.py
src/noseperf/wrappers/base.py
src/noseperf/wrappers/django.py
src/noseperf/wrappers/redis.py