Metadata-Version: 1.0
Name: nose-performance
Version: 0.4.0
Summary: A plugin for Nose for running performance tests
Home-page: https://github.com/disqus/nose-performance
Author: DISQUS
Author-email: opensource@disqus.com
License: Apache License 2.0
Platform: UNKNOWN
Classifier: Intended Audience :: Developers
Classifier: Intended Audience :: System Administrators
Classifier: Operating System :: OS Independent
Classifier: Topic :: Software Development
